latest_blender_url/__init__.py
latest_blender_url-0.1.6.dist-info/LICENSE
latest_blender_url-0.1.6.dist-info/METADATA
latest_blender_url-0.1.6.dist-info/WHEEL
latest_blender_url-0.1.6.dist-info/top_level.txt
latest_blender_url-0.1.6.dist-info/RECORD
