Metadata-Version: 2.1
Name: latest-blender-url
Version: 0.1.6
Summary: A python package that retrieves the latest Blender download URL
Home-page: https://github.com/justasb/latest_blender_url
Author: Justas Birgiolas
Author-email: justas@asu.edu
License: UNKNOWN
Platform: UNKNOWN
Classifier: Programming Language :: Python :: 3
Classifier: Programming Language :: Python :: 2
Classifier: License :: OSI Approved :: MIT License
Classifier: Operating System :: OS Independent
Requires-Dist: lxml
Requires-Dist: beautifulsoup4
